mqclient/__init__.py
mqclient/broker_client_interface.py
mqclient/broker_client_manager.py
mqclient/config.py
mqclient/log_msgs.py
mqclient/py.typed
mqclient/queue.py
mqclient/telemetry.py
mqclient/broker_clients/__init__.py
mqclient/broker_clients/apachepulsar.py
mqclient/broker_clients/nats.py
mqclient/broker_clients/rabbitmq.py
mqclient/broker_clients/utils.py
oms_mqclient-2.7.1.dist-info/licenses/LICENSE
tests/abstract_broker_client_tests/__init__.py
tests/abstract_broker_client_tests/integrate_broker_client_interface.py
tests/abstract_broker_client_tests/integrate_queue.py
tests/abstract_broker_client_tests/unit_tests.py
tests/abstract_broker_client_tests/utils.py
tests/integrate/__init__.py
tests/integrate/conftest.py
tests/integrate/test_nats.py
tests/integrate/test_pulsar.py
tests/integrate/test_rabbitmq.py
tests/unit/__init__.py
tests/unit/brokerless/test_broker_client_interface.py
tests/unit/brokerless/test_broker_client_manager.py
tests/unit/brokerless/test_init.py
tests/unit/brokerless/test_queue.py
tests/unit/pulsar/__init__.py
tests/unit/pulsar/test_pulsar.py
tests/unit/rabbitmq/__init__.py
tests/unit/rabbitmq/test_rabbitmq.py
oms_mqclient-2.7.1.dist-info/METADATA
oms_mqclient-2.7.1.dist-info/WHEEL
oms_mqclient-2.7.1.dist-info/top_level.txt
oms_mqclient-2.7.1.dist-info/RECORD
