Metadata-Version: 2.4
Name: oms-mqclient
Version: 2.7.1
Summary: A Message Queue Client API Supporting Apache Pulsar, RabbitMQ, and NATS.io
Author-email: WIPAC Developers <developers@icecube.wisc.edu>
License-Expression: MIT
Project-URL: Homepage, https://pypi.org/project/oms-mqclient/
Project-URL: Tracker, https://github.com/Observation-Management-Service/MQClient/issues
Project-URL: Source, https://github.com/Observation-Management-Service/MQClient
Keywords: Observation Management Service,Event Workflow Management System,EWMS,python message passing client,message passing,API,mq,apache,pulsar,pubsub,rabbitmq,pika,nats,nats.io
Classifier: Programming Language :: Python :: 3.10
Classifier: Programming Language :: Python :: 3.11
Classifier: Programming Language :: Python :: 3.12
Classifier: Programming Language :: Python :: 3.13
Requires-Python: <3.14,>=3.10
License-File: LICENSE
Requires-Dist: wipac-dev-tools
Requires-Dist: zstd
Provides-Extra: all
Requires-Dist: nats-py[nkeys]; extra == "all"
Requires-Dist: pika; extra == "all"
Requires-Dist: pulsar-client; extra == "all"
Provides-Extra: pulsar
Requires-Dist: pulsar-client; extra == "pulsar"
Provides-Extra: rabbitmq
Requires-Dist: pika; extra == "rabbitmq"
Provides-Extra: nats
Requires-Dist: nats-py[nkeys]; extra == "nats"
Provides-Extra: telemetry
Requires-Dist: wipac-telemetry; extra == "telemetry"
Provides-Extra: dev
Requires-Dist: asyncstdlib; extra == "dev"
Requires-Dist: coloredlogs; extra == "dev"
Requires-Dist: mock; extra == "dev"
Requires-Dist: mypy; extra == "dev"
Requires-Dist: pytest; extra == "dev"
Requires-Dist: pytest-asyncio; extra == "dev"
Requires-Dist: pytest-mock; extra == "dev"
Provides-Extra: integration
Requires-Dist: pytest-xdist; extra == "integration"
Requires-Dist: wipac-keycloak-rest-services; extra == "integration"
Requires-Dist: wipac-rest-tools; extra == "integration"
Provides-Extra: mypy
Requires-Dist: asyncstdlib; extra == "mypy"
Requires-Dist: coloredlogs; extra == "mypy"
Requires-Dist: mock; extra == "mypy"
Requires-Dist: mypy; extra == "mypy"
Requires-Dist: nats-py[nkeys]; extra == "mypy"
Requires-Dist: pika; extra == "mypy"
Requires-Dist: pulsar-client; extra == "mypy"
Requires-Dist: pytest; extra == "mypy"
Requires-Dist: pytest-asyncio; extra == "mypy"
Requires-Dist: pytest-mock; extra == "mypy"
Requires-Dist: pytest-xdist; extra == "mypy"
Requires-Dist: wipac-keycloak-rest-services; extra == "mypy"
Requires-Dist: wipac-rest-tools; extra == "mypy"
Requires-Dist: wipac-telemetry; extra == "mypy"
Dynamic: license-file
